sum_04734/__init__.py
sum_04734-0.0.1.dist-info/Licence.txt
sum_04734-0.0.1.dist-info/METADATA
sum_04734-0.0.1.dist-info/WHEEL
sum_04734-0.0.1.dist-info/top_level.txt
sum_04734-0.0.1.dist-info/RECORD
